instagram_posts_scraper/__init__.py
instagram_posts_scraper/example.py
instagram_posts_scraper/file_operation.py
instagram_posts_scraper/instagram_posts_scraper.py
instagram_posts_scraper/parse.py
instagram_posts_scraper/request.py
instagram_posts_scraper/scraper.py
instagram_posts_scraper/utils.py
instagram_posts_scraper/utils/__init__.py
instagram_posts_scraper/utils/utils.py
instagram_posts_scraper-0.0.6.dist-info/licenses/LICENSE
instagram_posts_scraper-0.0.6.dist-info/METADATA
instagram_posts_scraper-0.0.6.dist-info/WHEEL
instagram_posts_scraper-0.0.6.dist-info/top_level.txt
instagram_posts_scraper-0.0.6.dist-info/RECORD
