Metadata-Version: 2.4
Name: instagram-posts-scraper
Version: 0.0.6
Summary: Implement Instagram Posts Scraper for post data retrieval
Home-page: https://github.com/FaustRen/instagram-posts-scraper
Author: FaustRen
Author-email: faustren1z@gmail.com
License: MIT
Classifier: Programming Language :: Python :: 3.11
Classifier: License :: OSI Approved :: MIT License
Classifier: Operating System :: OS Independent
Requires-Python: >=3.11
License-File: LICENSE
Dynamic: author
Dynamic: author-email
Dynamic: classifier
Dynamic: description
Dynamic: description-content-type
Dynamic: home-page
Dynamic: license
Dynamic: license-file
Dynamic: requires-python
Dynamic: summary
